README.rst
setup.cfg
setup.py
repoman/__init__.py
repoman/changeset.py
repoman/commitmessage.py
repoman/depot.py
repoman/depot_manager.py
repoman/depot_operations.py
repoman/reference.py
repoman/repo_indexer.py
repoman/repository.py
repoman/roster.py
repoman/signature.py
repoman/git/__init__.py
repoman/git/depot_operations.py
repoman/git/pygitext.py
repoman/git/repository.py
repoman/hg/__init__.py
repoman/hg/depot_operations.py
repoman/hg/hglibext.py
repoman/hg/hgwebapi.py
repoman/hg/repository.py
repoman/repo_indexers/__init__.py
repoman/repo_indexers/base_indexer.py
repoman/repo_indexers/hgweb_indexer.py
repoman/utils/__init__.py
repoman/utils/introspection/__init__.py
repoman/utils/introspection/dynamic_class_loading.py
repoman_scm.egg-info/PKG-INFO
repoman_scm.egg-info/SOURCES.txt
repoman_scm.egg-info/dependency_links.txt
repoman_scm.egg-info/requires.txt
repoman_scm.egg-info/top_level.txt