Metadata-Version: 1.1
Name: repoman-scm
Version: 0.7.1
Summary: Library and tools to manage pools of code repositories
Home-page: https://github.com/tuenti/python-repoman
Author: Tuenti Technologies S.L.
Author-email: sre@tuenti.com
License: Apache Software License
Download-URL: https://github.com/tuenti/python-repoman/tarball/v0.7.1
Keywords: DVCS git mercurial
Platform: UNKNOWN
Classifier: Development Status :: 4 - Beta
Classifier: Intended Audience :: Developers
Classifier: License :: OSI Approved :: Apache Software License
Classifier: Programming Language :: Python
Classifier: Topic :: Software Development :: Version Control
